Workbook
Name Slicer_CATEGORY: #N/A
Name Slicer_TYPE: #N/A

Sheet DATA
A1: DATE | B1: DESCRIPTION | C1: CATEGORY | D1: TYPE | E1: AMOUNT
A2: 45662 | B2: Salary Credit | C2: Salary | D2: Income | E2: 45000
A3: 45665 | B3: Grocery Store | C3: Food | D3: Expense | E3: 2450.5
A4: 45669 | B4: Metro Recharge | C4: Transport | D4: Expense | E4: 850
A5: 45672 | B5: Netflix Subscription | C5: Entertainment | D5: Expense | E5: 649
A6: 45677 | B6: Electricity Bill | C6: Utilities | D6: Expense | E6: 1850.75
A7: 45682 | B7: Freelance Payment | C7: Freelance | D7: Income | E7: 8000
A8: 45690 | B8: Grocery Store | C8: Food | D8: Expense | E8: 2780.4
A9: 45693 | B9: Salary Credit | C9: Salary | D9: Income | E9: 45000
A10: 45698 | B10: Fuel Expense | C10: Transport | D10: Expense | E10: 2200
A11: 45702 | B11: Movie Tickets | C11: Entertainment | D11: Expense | E11: 900
A12: 45706 | B12: Pharmacy Purchase | C12: Health | D12: Expense | E12: 1250.25
A13: 45712 | B13: Online Shopping | C13: Shopping | D13: Expense | E13: 3500
... A43: 46009 | B43: Year-End Vacation | C43: Entertainment | D43: Expense | E43: 8500

Sheet SUMMARY
A1: MONTHLY SUMMARY TABLE | G1: SPEND BY CATEGORY
A2: MONTHS | B2: TOTAL INCOME | C2: TOTAL EXPENSES | D2: NET SAVINGS | E2: STATUS | G2: CATEGORY | H2: TOTAL SPENT
A3: JANUARY | B3: =IFERROR(SUMIFS(Table1[AMOUNT],Table1[TYPE],"Income",Table1[DATE],">="&DATE(2025,1,1),Table1[DATE],"<"&DATE(2025,2,1)),0) -> 53000 | C3: =SUMIFS(Table1[AMOUNT],Table1[TYPE],"Expense",Table1[DATE],">="&DATE(2025,1,1),Table1[DATE],"<"&DATE(2025,2,1)) -> 5800.25 | D3: =B3-C3 -> 47199.75 | E3: =IF(D3<0,"DEFICIT!",IF(D3/B3<0.1,"LOW SAVINGS",IF(D3/B3<0.3,"MODERATE","HEALTHY"))) -> HEALTHY | G3: Food | H3: =SUMIFS(Table1[AMOUNT],Table1[CATEGORY],SUMMARY!G3,Table1[TYPE],"Expense") -> 19463.75
A4: FEBRUARY | B4: =IFERROR(SUMIFS(Table1[AMOUNT],Table1[TYPE],"Income",Table1[DATE],">="&DATE(2025,2,1),Table1[DATE],"<"&DATE(2025,3,1)),"Not Found") -> 45000 | C4: =SUMIFS(Table1[AMOUNT],Table1[TYPE],"Expense",Table1[DATE],">="&DATE(2025,2,1),Table1[DATE],"<"&DATE(2025,3,1)) -> 10630.65 | D4: =B4-C4 -> 34369.35 | E4: =IF(D4<0,"DEFICIT!",IF(D4/B4<0.1,"LOW SAVINGS",IF(D4/B4<0.3,"MODERATE","HEALTHY"))) -> HEALTHY | G4: Transport | H4: =SUMIFS(Table1[AMOUNT],Table1[CATEGORY],SUMMARY!G4,Table1[TYPE],"Expense") -> 7100
A5: MARCH | B5: =IFERROR(SUMIFS(Table1[AMOUNT],Table1[TYPE],"Income",Table1[DATE],">="&DATE(2025,3,1),Table1[DATE],"<"&DATE(2025,4,1)),"Not Found") -> 54500 | C5: =SUMIFS(Table1[AMOUNT],Table1[TYPE],"Expense",Table1[DATE],">="&DATE(2025,3,1),Table1[DATE],"<"&DATE(2025,4,1)) -> 6259.8 | D5: =B5-C5 -> 48240.2 | E5: =IF(D5<0,"DEFICIT!",IF(D5/B5<0.1,"LOW SAVINGS",IF(D5/B5<0.3,"MODERATE","HEALTHY"))) -> HEALTHY | G5: Entertainment | H5: =SUMIFS(Table1[AMOUNT],Table1[CATEGORY],SUMMARY!G5,Table1[TYPE],"Expense") -> 10918
A6: APRIL | B6: =IFERROR(SUMIFS(Table1[AMOUNT],Table1[TYPE],"Income",Table1[DATE],">="&DATE(2025,4,1),Table1[DATE],"<"&DATE(2025,5,1)),"Not Found") -> 45000 | C6: =SUMIFS(Table1[AMOUNT],Table1[TYPE],"Expense",Table1[DATE],">="&DATE(2025,4,1),Table1[DATE],"<"&DATE(2025,5,1)) -> 11695.65 | D6: =B6-C6 -> 33304.35 | E6: =IF(D6<0,"DEFICIT!",IF(D6/B6<0.1,"LOW SAVINGS",IF(D6/B6<0.3,"MODERATE","HEALTHY"))) -> HEALTHY | G6: Utilities | H6: =SUMIFS(Table1[AMOUNT],Table1[CATEGORY],SUMMARY!G6,Table1[TYPE],"Expense") -> 7099.75
A7: MAY | B7: =IFERROR(SUMIFS(Table1[AMOUNT],Table1[TYPE],"Income",Table1[DATE],">="&DATE(2025,5,1),Table1[DATE],"<"&DATE(2025,6,1)),"Not Found") -> 58000 | C7: =SUMIFS(Table1[AMOUNT],Table1[TYPE],"Expense",Table1[DATE],">="&DATE(2025,5,1),Table1[DATE],"<"&DATE(2025,6,1)) -> 4069.25 | D7: =B7-C7 -> 53930.75 | E7: =IF(D7<0,"DEFICIT!",IF(D7/B7<0.1,"LOW SAVINGS",IF(D7/B7<0.3,"MODERATE","HEALTHY"))) -> HEALTHY | G7: Freelance | H7: =SUMIFS(Table1[AMOUNT],Table1[CATEGORY],SUMMARY!G7,Table1[TYPE],"Expense") -> 0
A8: JUNE | B8: =SUMIFS(Table1[AMOUNT],Table1[TYPE],"Income",Table1[DATE],">="&DATE(2025,6,1),Table1[DATE],"<"&DATE(2025,7,1)) -> 47000 | C8: =SUMIFS(Table1[AMOUNT],Table1[TYPE],"Expense",Table1[DATE],">="&DATE(2025,6,1),Table1[DATE],"<"&DATE(2025,7,1)) -> 9025.4 | D8: =B8-C8 -> 37974.6 | E8: =IF(D8<0,"DEFICIT!",IF(D8/B8<0.1,"LOW SAVINGS",IF(D8/B8<0.3,"MODERATE","HEALTHY"))) -> HEALTHY | G8: Health | H8: =SUMIFS(Table1[AMOUNT],Table1[CATEGORY],SUMMARY!G8,Table1[TYPE],"Expense") -> 7750.25
A9: JULY | B9: =SUMIFS(Table1[AMOUNT],Table1[TYPE],"Income",Table1[DATE],">="&DATE(2025,7,1),Table1[DATE],"<"&DATE(2025,8,1)) -> 47000 | C9: =SUMIFS(Table1[AMOUNT],Table1[TYPE],"Expense",Table1[DATE],">="&DATE(2025,7,1),Table1[DATE],"<"&DATE(2025,8,1)) -> 5650.75 | D9: =B9-C9 -> 41349.25 | E9: =IF(D9<0,"DEFICIT!",IF(D9/B9<0.1,"LOW SAVINGS",IF(D9/B9<0.3,"MODERATE","HEALTHY"))) -> HEALTHY | G9: Shopping | H9: =SUMIFS(Table1[AMOUNT],Table1[CATEGORY],SUMMARY!G9,Table1[TYPE],"Expense") -> 18000
A10: AUGUST | B10: =SUMIFS(Table1[AMOUNT],Table1[TYPE],"Income",Table1[DATE],">="&DATE(2025,8,1),Table1[DATE],"<"&DATE(2025,9,1)) -> 50000 | C10: =SUMIFS(Table1[AMOUNT],Table1[TYPE],"Expense",Table1[DATE],">="&DATE(2025,8,1),Table1[DATE],"<"&DATE(2025,9,1)) -> 0 | D10: =B10-C10 -> 50000 | E10: =IF(D10<0,"DEFICIT!",IF(D10/B10<0.1,"LOW SAVINGS",IF(D10/B10<0.3,"MODERATE","HEALTHY"))) -> HEALTHY
A11: SEPTEMBER | B11: =SUMIFS(Table1[AMOUNT],Table1[TYPE],"Income",Table1[DATE],">="&DATE(2025,9,1),Table1[DATE],"<"&DATE(2025,10,1)) -> 0 | C11: =SUMIFS(Table1[AMOUNT],Table1[TYPE],"Expense",Table1[DATE],">="&DATE(2025,9,1),Table1[DATE],"<"&DATE(2025,10,1)) -> 2200 | D11: =B11-C11 -> -2200 | E11: =IF(D11<0,"DEFICIT!",IF(D11/B11<0.1,"LOW SAVINGS",IF(D11/B11<0.3,"MODERATE","HEALTHY"))) -> DEFICIT! | G11: Highest Savings Month | H11: =INDEX(A3:A14,MATCH(MAX(D3:D14),D3:D14,0),1) -> MAY
A12: OCTOBER | B12: =SUMIFS(Table1[AMOUNT],Table1[TYPE],"Income",Table1[DATE],">="&DATE(2025,10,1),Table1[DATE],"<"&DATE(2025,11,1)) -> 12000 | C12: =SUMIFS(Table1[AMOUNT],Table1[TYPE],"Expense",Table1[DATE],">="&DATE(2025,10,1),Table1[DATE],"<"&DATE(2025,11,1)) -> 0 | D12: =B12-C12 -> 12000 | E12: =IF(D12<0,"DEFICIT!",IF(D12/B12<0.1,"LOW SAVINGS",IF(D12/B12<0.3,"MODERATE","HEALTHY"))) -> HEALTHY | G12: Lowest Savings Month | H12: =INDEX(A3:A14,MATCH(MIN(D3:D14),D3:D14,0),1) -> NOVEMBER
A13: NOVEMBER | B13: =SUMIFS(Table1[AMOUNT],Table1[TYPE],"Income",Table1[DATE],">="&DATE(2025,11,1),Table1[DATE],"<"&DATE(2025,12,1)) -> 0 | C13: =SUMIFS(Table1[AMOUNT],Table1[TYPE],"Expense",Table1[DATE],">="&DATE(2025,11,1),Table1[DATE],"<"&DATE(2025,12,1)) -> 6500 | D13: =B13-C13 -> -6500 | E13: =IF(D13<0,"DEFICIT!",IF(D13/B13<0.1,"LOW SAVINGS",IF(D13/B13<0.3,"MODERATE","HEALTHY"))) -> DEFICIT!
A14: DECEMBER | B14: =SUMIFS(Table1[AMOUNT],Table1[TYPE],"Income",Table1[DATE],">="&DATE(2025,12,1)) -> 50000 | C14: =SUMIFS(Table1[AMOUNT],Table1[TYPE],"Expense",Table1[DATE],">="&DATE(2025,12,1)) -> 8500 | D14: =B14-C14 -> 41500 | E14: =IF(D14<0,"DEFICIT!",IF(D14/B14<0.1,"LOW SAVINGS",IF(D14/B14<0.3,"MODERATE","HEALTHY"))) -> HEALTHY
A16: Total Annual Income | C16: =SUM(B3:B14) -> 461500
A17: Total Annual Expenses | C17: =SUM(C3:C14) -> 70331.75
A18: Net Annual Savings | C18: =C16-C17 -> 391168.25
A19: Savings Rate % | C19: =(C18/C16) -> 0.84760184

Sheet CHART

Sheet BUDGETS
A1: CATEGORY | B1: MONTHLY BUDGET | C1: ANNUAL BUDGET | D1: ACTUAL SPENT | E1: NET | F1: OVER/UNDER BUDGET
A2: Food | B2: 4000 | C2: =B2*12 -> 48000 | D2: =VLOOKUP(A2,SUMMARY!G3:H9,2,) -> 19463.75 | E2: =C2-D2 -> 28536.25 | F2: =IF(C2-D2>0,"Under Budget", IF(C2-D2<0,"Over Budget","On Budget")) -> Under Budget
A3: Transport | B3: 2000 | C3: =B3*12 -> 24000 | D3: =VLOOKUP(A3,SUMMARY!G4:H10,2,) -> 7100 | E3: =C3-D3 -> 16900 | F3: =IF(C3-D3>0,"Under Budget", IF(C3-D3<0,"Over Budget","On Budget")) -> Under Budget
A4: Entertainment | B4: 1000 | C4: =B4*12 -> 12000 | D4: =VLOOKUP(A4,SUMMARY!G5:H11,2,) -> 10918 | E4: =C4-D4 -> 1082 | F4: =IF(C4-D4>0,"Under Budget", IF(C4-D4<0,"Over Budget","On Budget")) -> Under Budget
A5: Utilities | B5: 2000 | C5: =B5*12 -> 24000 | D5: =VLOOKUP(A5,SUMMARY!G6:H12,2,) -> 7099.75 | E5: =C5-D5 -> 16900.25 | F5: =IF(C5-D5>0,"Under Budget", IF(C5-D5<0,"Over Budget","On Budget")) -> Under Budget
A6: Freelance | B6: 500 | C6: =B6*12 -> 6000 | D6: =VLOOKUP(A6,SUMMARY!G7:H13,2,) -> 0 | E6: =C6-D6 -> 6000 | F6: =IF(C6-D6>0,"Under Budget", IF(C6-D6<0,"Over Budget","On Budget")) -> Under Budget
A7: Health | B7: 1000 | C7: =B7*12 -> 12000 | D7: =VLOOKUP(A7,SUMMARY!G8:H14,2,) -> 7750.25 | E7: =C7-D7 -> 4249.75 | F7: =IF(C7-D7>0,"Under Budget", IF(C7-D7<0,"Over Budget","On Budget")) -> Under Budget
A8: Shopping | B8: 2500 | C8: =B8*12 -> 30000 | D8: =VLOOKUP(A8,SUMMARY!G9:H15,2,) -> 18000 | E8: =C8-D8 -> 12000 | F8: =IF(C8-D8>0,"Under Budget", IF(C8-D8<0,"Over Budget","On Budget")) -> Under Budget

Sheet PIVOT1
A2: SAME TABLE AS MONTHLY INCOME vs EXPENSES IN SUMMARY BUT DONE USING PIVOT IN CONTRAST TO SUMIFS WHILE ALSO MAKING IT DYNAMIC
A3: Sum of AMOUNT | B3: Column Labels
A4: Row Labels | B4: Expense | C4: Income | D4: Grand Total
A5: Jan | B5: 5800.25 | C5: 53000 | D5: 58800.25
A6: Feb | B6: 10630.65 | C6: 45000 | D6: 55630.65
A7: Mar | B7: 6259.8 | C7: 54500 | D7: 60759.8
A8: Apr | B8: 11695.65 | C8: 45000 | D8: 56695.65
A9: May | B9: 4069.25 | C9: 58000 | D9: 62069.25
A10: Jun | B10: 9025.4 | C10: 47000 | D10: 56025.4
A11: Jul | B11: 5650.75 | C11: 47000 | D11: 52650.75
A12: Aug | C12: 50000 | D12: 50000
A13: Sep | B13: 2200 | D13: 2200
A14: Oct | C14: 12000 | D14: 12000
A15: Nov | B15: 6500 | D15: 6500
A16: Dec | B16: 8500 | C16: 50000 | D16: 58500
A17: Grand Total | B17: 70331.75 | C17: 461500 | D17: 531831.75

Sheet PIVOT2
A1: TYPE | B1: (All) | D1: SAME TABLE AS 'SPEND BY CATEGORY' IN SUMMARY BUT DONE USING PIVOT IN CONTRAST TO SUMIFS WHILE ALSO MAKING IT DYNAMIC
A3: Row Labels | B3: Sum of AMOUNT
A4: Entertainment | B4: 10918
A5: Food | B5: 19463.75
A6: Freelance | B6: 40500
A7: Health | B7: 7750.25
A8: Salary | B8: 421000
A9: Shopping | B9: 18000
A10: Transport | B10: 7100
A11: Utilities | B11: 7099.75
A12: Grand Total | B12: 531831.75
